{"cameraMode":{"drawMode":0,"name":"Shaded","section":"Shading Mode"},"sceneLighting":true,"audioPlay":false,"sceneViewState":{"m_AlwaysRefresh":false,"showFog":false,"showSkybox":false,"showFlares":false,"showImageEffects":false,"showParticleSystems":false,"showVisualEffectGraphs":false,"m_FxEnabled":true},"in2DMode":false,"pivot":{"x":101.7438735961914,"y":56.58734130859375,"z":-61.66130065917969},"rotation":{"x":0.27767953276634219,"y":0.15052443742752076,"z":-0.04409732297062874,"w":0.947788655757904},"size":174.78878784179688,"orthographic":false}